[
    {
        "name": "晚疫病",
        "id": 0,
        "detail": "番茄晚疫病",
        "itemStyle": {
            "color": "blue"
        }
    },
    {
        "name": "使用杀菌...",
        "id": 1,
        "category": 1,
        "detail": "使用杀菌剂：可选择合适的<br>杀菌剂对番茄植株进行喷洒，以<br>抑制病原真菌的生长和繁殖。<br>使用杀菌剂时，一定要严格按照<br>产品说明和农药标签上的指示使用，<br>保证安全和有效。"
    },
    {
        "name": "调整灌溉...",
        "id": 2,
        "category": 2,
        "detail": "调整灌溉：适当控制灌溉水量，<br>避免使植株和叶片过于潮湿，<br>有助于减少病害的发生。"
    },
    {
        "name": "病害监测...",
        "id": 3,
        "category": 2,
        "detail": "病害监测与早期发现：定期巡视<br>番茄田地，及时发现植株上出现的<br>异常情况，并采取措施进行防治。"
    },
    {
        "name": "移栽健康...",
        "id": 4,
        "category": 4,
        "detail": "移栽健康植株：选择健康的番茄<br>幼苗进行移栽，避免导入病原菌。"
    },
    {
        "name": "合理施肥...",
        "id": 5,
        "category": 4,
        "detail": "合理施肥：番茄植株养分供应充<br>足有助于增强其抵抗病害的能力，<br>因此合理施肥也是预防番茄晚疫<br>病的重要措施。"
    }
]